package lasm;

/* compiled from: src */
/* loaded from: classes.dex */
public interface b {
    public static final String[] e = {"<EOF>", "\" \"", "\"\\t\"", "\"\\f\"", "<COMMENT>", "\"MOVE\"", "\"LOADK\"", "\"LOADBOOL\"", "\"LOADNIL\"", "\"GETUPVAL\"", "\"GETTABUP\"", "\"GETTABLE\"", "\"SETTABUP\"", "\"SETUPVAL\"", "\"SETTABLE\"", "\"NEWTABLE\"", "\"SELF\"", "\"ADD\"", "\"SUB\"", "\"MUL\"", "\"DIV\"", "\"MOD\"", "\"POW\"", "\"UNM\"", "\"NOT\"", "\"LEN\"", "\"CONCAT\"", "\"JMP\"", "\"EQ\"", "\"LT\"", "\"LE\"", "\"TEST\"", "\"TESTSET\"", "\"CALL\"", "\"TAILCALL\"", "\"RETURN\"", "\"FORLOOP\"", "\"FORPREP\"", "\"TFORCALL\"", "\"TFORLOOP\"", "\"SETLIST\"", "\"CLOSURE\"", "\"VARARG\"", "\"IDIV\"", "\"BNOT\"", "\"BAND\"", "\"BOR\"", "\"BXOR\"", "\"SHL\"", "\"SHR\"", "\"CONST\"", "\"FUNC[\"", "\"GOTO[\"", "\"OP\"", "\"SET_TOP\"", "\"SKIP_NEXT\"", "\"nil\"", "\"true\"", "\"false\"", "<V_NAME>", "<SINT>", "<NAME>", "\".source\"", "\".linedefined\"", "\".lastlinedefined\"", "\".numparams\"", "\".is_vararg\"", "\".maxstacksize\"", "\".upval\"", "\".line\"", "\".local\"", "\".end local\"", "\".func\"", "\".end\"", "<EOL>", "\"..\"", "<LABEL>", "<V>", "<U>", "<INT>", "<HEX>", "<STRING>", "<QUOTED>", "<NL>", "<FLOAT>", "<DIGIT>", "<EXP>", "<HEXDIGIT>", "\"[\"", "\"]\""};
}
